appinspect_submit/__init__.py
appinspect_submit/__main__.py
appinspect_submit/config.py
appinspect_submit/constants.py
appinspect_submit-0.1.4.dist-info/LICENSE
appinspect_submit-0.1.4.dist-info/METADATA
appinspect_submit-0.1.4.dist-info/WHEEL
appinspect_submit-0.1.4.dist-info/entry_points.txt
appinspect_submit-0.1.4.dist-info/RECORD
